django_web_app-0.0.8.dist-info/LICENSE.txt
django_web_app-0.0.8.dist-info/METADATA
django_web_app-0.0.8.dist-info/RECORD
django_web_app-0.0.8.dist-info/WHEEL
django_web_app-0.0.8.dist-info/top_level.txt
web_app/__init__.py
web_app/admin.py
web_app/apps.py
web_app/models.py
web_app/tests.py
web_app/urls.py
web_app/__pycache__/__init__.cpython-36.pyc
web_app/__pycache__/admin.cpython-36.pyc
web_app/__pycache__/models.cpython-36.pyc
web_app/__pycache__/urls.cpython-36.pyc
web_app/migrations/__init__.py
web_app/migrations/__pycache__/__init__.cpython-36.pyc
web_app/static/web_app/images/IMG_3517.JPG
web_app/templates/web_app/index.html
web_app/views/index.py
web_app/views/__pycache__/index.cpython-36.pyc
